hypergraph.cpython-36m-x86_64-linux-gnu.so
hypergraph-0.5.0.dist-info/RECORD
hypergraph-0.5.0.dist-info/top_level.txt
hypergraph-0.5.0.dist-info/WHEEL
hypergraph-0.5.0.dist-info/METADATA
