Metadata-Version: 1.0
Name: hypergraph
Version: 0.5.0
Summary: Reversed mode second order automatic differentiation for python
Home-page: https://github.com/oberbichler/HyperGraph
Author: Thomas Oberbichler
Author-email: thomas.oberbichler@gmail.com
License: UNKNOWN
Platform: UNKNOWN
